esphomeflasher/__init__.py
esphomeflasher/__main__.py
esphomeflasher/common.py
esphomeflasher/const.py
esphomeflasher/gui.py
esphomeflasher/helpers.py
esphomeflasher-1.3.0.dist-info/LICENSE
esphomeflasher-1.3.0.dist-info/METADATA
esphomeflasher-1.3.0.dist-info/WHEEL
esphomeflasher-1.3.0.dist-info/entry_points.txt
esphomeflasher-1.3.0.dist-info/top_level.txt
esphomeflasher-1.3.0.dist-info/RECORD
