Metadata-Version: 2.1
Name: esphomeflasher
Version: 1.3.0
Summary: ESP8266/ESP32 firmware flasher for ESPHome
Home-page: https://github.com/esphome/esphome-flasher
Author: ESPHome
Author-email: contact@esphome.io
License: MIT
Download-URL: https://github.com/esphome/esphome-flasher/archive/1.3.0.zip
Keywords: home,automation
Platform: any
Requires-Python: >=3.5,<4.0
Requires-Dist: esptool (==2.8)
Requires-Dist: requests (<3,>=2.24.0)
Requires-Dist: wxpython (<5.0,>=4.0)
